barbell2_bodycomp/__init__.py
barbell2_bodycomp/calculator.py
barbell2_bodycomp/contour.py
barbell2_bodycomp/seg.py
barbell2_bodycomp/selectroi.py
barbell2_bodycomp/selectslice.py
barbell2_bodycomp/totalseg.py
barbell2_bodycomp/utils.py
barbell2_bodycomp/convert/__init__.py
barbell2_bodycomp/convert/dcm2nifti.py
barbell2_bodycomp/convert/dcm2npy.py
barbell2_bodycomp/convert/dcm2raw.py
barbell2_bodycomp/convert/dcmscale.py
barbell2_bodycomp/convert/npy2dcm.py
barbell2_bodycomp/convert/npy2nifti.py
barbell2_bodycomp/convert/npy2nrrd.py
barbell2_bodycomp/convert/npy2png.py
barbell2_bodycomp/convert/tag2dcm.py
barbell2_bodycomp/convert/tag2npy.py
barbell2_bodycomp-0.26.0.dist-info/METADATA
barbell2_bodycomp-0.26.0.dist-info/WHEEL
barbell2_bodycomp-0.26.0.dist-info/entry_points.txt
barbell2_bodycomp-0.26.0.dist-info/top_level.txt
barbell2_bodycomp-0.26.0.dist-info/RECORD
