Metadata-Version: 2.1
Name: barbell2-bodycomp
Version: 0.26.0
Summary: components for command-line body composition analysis
Home-page: https://github.com/rbrecheisen/barbell2_bodycomp
Author: Ralph Brecheisen
Author-email: r.brecheisen@maastrichtuniversity.nl
License: MIT license
Keywords: barbell2_bodycomp
Platform: UNKNOWN
Classifier: Development Status :: 2 - Pre-Alpha
Classifier: Intended Audience :: Developers
Classifier: License :: OSI Approved :: MIT License
Classifier: Natural Language :: English
Classifier: Programming Language :: Python :: 3
Classifier: Programming Language :: Python :: 3.5
Classifier: Programming Language :: Python :: 3.6
Classifier: Programming Language :: Python :: 3.7
Classifier: Programming Language :: Python :: 3.8
Requires-Python: >=3.5
Requires-Dist: numpy
Requires-Dist: pydicom
Requires-Dist: pynrrd
Requires-Dist: matplotlib
Requires-Dist: nibabel
Requires-Dist: tensorflow
Requires-Dist: totalsegmentator
